[{"_id":"5e802d22e410ce6cd8d87d87","kpi_name":"ccs","business_unit":"retail","level":"country","country":"india","resolution_time":"less than 2 days","resolved_cases":60,"total_complaints":120,"data_type":"ytm","date":"2020-02-10T18:30:00.000Z","__v":0,"createdAt":"2020-03-29T05:07:46.527Z","updatedAt":"2020-03-29T05:07:46.527Z"},{"_id":"5e802d22e410ce6cd8d87d8a","kpi_name":"ccs","business_unit":"retail","level":"country","country":"india","resolution_time":"more than 10 days","resolved_cases":10,"total_complaints":120,"data_type":"ytm","date":"2020-02-10T18:30:00.000Z","__v":0,"createdAt":"2020-03-29T05:07:46.528Z","updatedAt":"2020-03-29T05:07:46.528Z"},{"_id":"5e802d22e410ce6cd8d87d89","kpi_name":"ccs","business_unit":"retail","level":"country","country":"india","resolution_time":"6 - 10 days","resolved_cases":10,"total_complaints":120,"data_type":"ytm","date":"2020-02-10T18:30:00.000Z","__v":0,"createdAt":"2020-03-29T05:07:46.528Z","updatedAt":"2020-03-29T05:07:46.528Z"},{"_id":"5e802d22e410ce6cd8d87d88","kpi_name":"ccs","business_unit":"retail","level":"country","country":"india","resolution_time":"2 - 5 days","resolved_cases":20,"total_complaints":120,"data_type":"ytm","date":"2020-02-10T18:30:00.000Z","__v":0,"createdAt":"2020-03-29T05:07:46.528Z","updatedAt":"2020-03-29T05:07:46.528Z"},{"_id":"5e85efd9b2685a86440e27d4","kpi_name":"ccs","business_unit":"lpg","level":"country","country":"india","resolution_time":"less than 2 days","resolved_cases":60,"total_complaints":120,"data_type":"ytm","date":"2020-02-10T18:30:00.000Z","__v":0,"createdAt":"2020-03-29T05:07:46.527Z","updatedAt":"2020-03-29T05:07:46.527Z"},{"_id":"5e85efd9b2685a86440e27d7","kpi_name":"ccs","business_unit":"lpg","level":"country","country":"india","resolution_time":"more than 10 days","resolved_cases":10,"total_complaints":120,"data_type":"ytm","date":"2020-02-10T18:30:00.000Z","__v":0,"createdAt":"2020-03-29T05:07:46.528Z","updatedAt":"2020-03-29T05:07:46.528Z"},{"_id":"5e85efd9b2685a86440e27d5","kpi_name":"ccs","business_unit":"lpg","level":"country","country":"india","resolution_time":"2 - 5 days","resolved_cases":20,"total_complaints":120,"data_type":"ytm","date":"2020-02-10T18:30:00.000Z","__v":0,"createdAt":"2020-03-29T05:07:46.528Z","updatedAt":"2020-03-29T05:07:46.528Z"},{"_id":"5e85efd9b2685a86440e27d6","kpi_name":"ccs","business_unit":"lpg","level":"country","country":"india","resolution_time":"6 - 10 days","resolved_cases":10,"total_complaints":120,"data_type":"ytm","date":"2020-02-10T18:30:00.000Z","__v":0,"createdAt":"2020-03-29T05:07:46.528Z","updatedAt":"2020-03-29T05:07:46.528Z"},{"customer_satisfation":{"actual":33,"growth":3},"_id":"5e99f1fb7fe6f00cd38b0b64","kpi_name":"ccs","business_unit":"atf","level":"country","country":"india","resolution_time":"less than 2 days","resolved_cases":60,"total_complaints":120,"data_type":"ytm","date":"2020-02-10T18:30:00.000Z","__v":0,"createdAt":"2020-03-29T05:07:46.527Z","updatedAt":"2020-03-29T05:07:46.527Z"},{"customer_satisfation":{"actual":33,"growth":3},"_id":"5e99f1fb7fe6f00cd38b0b65","kpi_name":"ccs","business_unit":"atf","level":"country","country":"india","resolution_time":"more than 10 days","resolved_cases":10,"total_complaints":120,"data_type":"ytm","date":"2020-02-10T18:30:00.000Z","__v":0,"createdAt":"2020-03-29T05:07:46.528Z","updatedAt":"2020-03-29T05:07:46.528Z"},{"customer_satisfation":{"actual":33,"growth":3},"_id":"5e99f1fb7fe6f00cd38b0b66","kpi_name":"ccs","business_unit":"atf","level":"country","country":"india","resolution_time":"2 - 5 days","resolved_cases":20,"total_complaints":120,"data_type":"ytm","date":"2020-02-10T18:30:00.000Z","__v":0,"createdAt":"2020-03-29T05:07:46.528Z","updatedAt":"2020-03-29T05:07:46.528Z"},{"customer_satisfation":{"actual":33,"growth":3},"_id":"5e99f1fb7fe6f00cd38b0b67","kpi_name":"ccs","business_unit":"atf","level":"country","country":"india","resolution_time":"6 - 10 days","resolved_cases":10,"total_complaints":120,"data_type":"ytm","date":"2020-02-10T18:30:00.000Z","__v":0,"createdAt":"2020-03-29T05:07:46.528Z","updatedAt":"2020-03-29T05:07:46.528Z"},{"customer_satisfation":{"actual":33,"growth":3},"_id":"5e9fd1004eaf8328db68a369","kpi_name":"ccs","business_unit":"inc","level":"country","country":"india","resolution_time":"2 - 5 days","resolved_cases":20,"total_complaints":120,"data_type":"ytm","date":"2020-02-10T18:30:00.000Z","__v":0,"createdAt":"2020-03-29T05:07:46.528Z","updatedAt":"2020-03-29T05:07:46.528Z"},{"customer_satisfation":{"actual":33,"growth":3},"_id":"5e9fd1004eaf8328db68a36a","kpi_name":"ccs","business_unit":"inc","level":"country","country":"india","resolution_time":"less than 2 days","resolved_cases":60,"total_complaints":120,"data_type":"ytm","date":"2020-02-10T18:30:00.000Z","__v":0,"createdAt":"2020-03-29T05:07:46.527Z","updatedAt":"2020-03-29T05:07:46.527Z"},{"customer_satisfation":{"actual":33,"growth":3},"_id":"5e9fd1004eaf8328db68a368","kpi_name":"ccs","business_unit":"inc","level":"country","country":"india","resolution_time":"6 - 10 days","resolved_cases":10,"total_complaints":120,"data_type":"ytm","date":"2020-02-10T18:30:00.000Z","__v":0,"createdAt":"2020-03-29T05:07:46.528Z","updatedAt":"2020-03-29T05:07:46.528Z"},{"customer_satisfation":{"actual":33,"growth":3},"_id":"5e9fd1004eaf8328db68a36b","kpi_name":"ccs","business_unit":"inc","level":"country","country":"india","resolution_time":"more than 10 days","resolved_cases":10,"total_complaints":120,"data_type":"ytm","date":"2020-02-10T18:30:00.000Z","__v":0,"createdAt":"2020-03-29T05:07:46.528Z","updatedAt":"2020-03-29T05:07:46.528Z"}]